rdreturnnotice/EcsInterface.py
rdreturnnotice/__init__.py
rdreturnnotice/mainModel.py
rdreturnnotice/metadata.py
rdreturnnotice/operation.py
rdreturnnotice/utility.py
rdreturnsales/EcsInterface.py
rdreturnsales/__init__.py
rdreturnsales/mainModel.py
rdreturnsales/metadata.py
rdreturnsales/operation.py
rdreturnsales/utility.py
rdreturnsales-1.2.3.dist-info/METADATA
rdreturnsales-1.2.3.dist-info/NoticeOfReturn.py
rdreturnsales-1.2.3.dist-info/WHEEL
rdreturnsales-1.2.3.dist-info/top_level.txt
rdreturnsales-1.2.3.dist-info/RECORD
